{
  "main": [
    {
      "label": "Getting Started",
      "items": [
        {
          "label": "[document] Introduction",
          "autogenerate": { "directory": "getting-started/introduction" }
        }
      ]
    },
    {
      "label": "About Us",
      "items": [
        {
          "label": "[document] Mission, Vision & Values",
          "slug": "about-us/mission"
        },
        {
          "label": "[document] Co-op Structure & Model",
          "slug": "about-us/model"
        },
        {
          "label": "[document] Membership & Governance",
          "items": [
            {
              "label": "[document] Membership",
              "autogenerate": { "directory": "about-us/membership-governance/membership" }
            },
            {
              "label": "[document] Governance",
              "autogenerate": { "directory": "about-us/membership-governance/governance" }
            },
            {
              "label": "[document] Financial Transparency",
              "slug": "about-us/membership-governance/financial"
            }
          ]
        },
        {
          "label": "[document] Legal Documents & Policies",
          "slug": "about-us/legal"
        }
      ]
    },
    {
      "label": "Resources",
      "autogenerate": { "directory": "resources" }
    }
  ]
}
